<?xml version="1.0" encoding="UTF-8"?>
<!DOCTYPE suite SYSTEM "http://testng.org/testng-1.0.dtd">

<suite name="appiunTestDemo">
  <test name="127.0.0.1:62001">
    <parameter name="deviceName" value="127.0.0.1:62001"/>
    <parameter name="platformVersion" value="4.4"/>
    <parameter name="port" value="9002"/>
    <classes>
      <class name="com.cpeoc.appiunTestDemo.test.Fssss"/>
      <class name="com.cpeoc.appiunTestDemo.test.xx.Xxxxx"/>
    </classes>
  </test>
  <test name="fe3123d2">
    <parameter name="deviceName" value="fe3123d2"/>
    <parameter name="platformVersion" value="6.0"/>
    <parameter name="port" value="9003"/>
    <classes>
      <class name="com.cpeoc.appiunTestDemo.test.xx.CopyOfXzzzz"/>
    </classes>
  </test>
</suite>
